seven_framework/__init__.py
seven_framework/base_model.py
seven_framework/clickhouse.py
seven_framework/coding.py
seven_framework/config.py
seven_framework/crypto.py
seven_framework/csv.py
seven_framework/dict.py
seven_framework/es.py
seven_framework/excel.py
seven_framework/file.py
seven_framework/host.py
seven_framework/http.py
seven_framework/ip.py
seven_framework/json.py
seven_framework/log.py
seven_framework/memcached.py
seven_framework/mongodb.py
seven_framework/mysql.py
seven_framework/notice.py
seven_framework/os.py
seven_framework/powerjob.py
seven_framework/qr_code.py
seven_framework/redis.py
seven_framework/sign.py
seven_framework/time.py
seven_framework/uuid.py
seven_framework/wechat.py
seven_framework/work_wechat.py
seven_framework/console/__init__.py
seven_framework/console/base_console.py
seven_framework/message_queue/__init__.py
seven_framework/message_queue/rabbit.py
seven_framework/message_queue/rocket.py
seven_framework/web_tornado/__init__.py
seven_framework/web_tornado/base_tornado.py
seven_framework/web_tornado/monitor.py
seven_framework/web_tornado/base_handler/__init__.py
seven_framework/web_tornado/base_handler/base_api_handler.py
seven_framework/web_tornado/base_handler/base_cookie_handler.py
seven_framework/web_tornado/base_handler/base_handler.py
seven_framework-1.4.2.dist-info/LICENSE
seven_framework-1.4.2.dist-info/METADATA
seven_framework-1.4.2.dist-info/WHEEL
seven_framework-1.4.2.dist-info/top_level.txt
seven_framework-1.4.2.dist-info/RECORD
