Metadata-Version: 2.1
Name: seven-framework
Version: 1.4.2
Summary: seven framework
Home-page: http://gitlab.tdtech.gao7.com/python/seven_framework
Author: seven
Author-email: tech@gao7.com
License: MIT
Platform: UNKNOWN
Classifier: Topic :: Software Development :: Libraries :: Python Modules
Classifier: Programming Language :: Python
Classifier: Programming Language :: Python :: 3.4
Classifier: Programming Language :: Python :: 3.5
Classifier: Programming Language :: Python :: 3.5
Classifier: Programming Language :: Python :: 3.6
Classifier: Programming Language :: Python :: 3.7
Classifier: Programming Language :: Python :: 3.8
Classifier: Programming Language :: Python :: 3.9
Classifier: Programming Language :: Python :: 3.10
Classifier: Programming Language :: Python :: 3.11
Classifier: Programming Language :: Python :: 3.12
Classifier: Programming Language :: Python :: 3.13
Requires-Python: ~=3.4
Requires-Dist: elasticsearch (<=7.6.0)
Requires-Dist: requests (>=2.23.0)
Requires-Dist: PyMySQL (>=1.0.2)
Requires-Dist: python-dateutil (>=2.8.1)
Requires-Dist: redis (>=5.0.7)
Requires-Dist: pycryptodome (>=3.8.0)
Requires-Dist: tornado (==6.0.4)
Requires-Dist: bleach (>=3.1.5)
Requires-Dist: pycket (>=0.3.0)
Requires-Dist: ufile (>=3.2.2)
Requires-Dist: ks3sdk (>=1.0.16)
Requires-Dist: oss2 (>=2.13.1)
Requires-Dist: boto3 (>=1.20.37)
Requires-Dist: cos-python-sdk-v5 (>=1.9.0)
Requires-Dist: bce-python-sdk (>=0.8.61)
Requires-Dist: DBUtils (==1.3)
Requires-Dist: openpyxl (>=3.0.3)
Requires-Dist: xlwt (>=1.3.0)
Requires-Dist: xlrd (>=1.2.0)
Requires-Dist: xlutils (>=2.0.0)
Requires-Dist: qrcode (>=6.1)
Requires-Dist: Pillow (>=7.1.2)
Requires-Dist: threadpool (>=1.3.2)
Requires-Dist: filechunkio (>=1.8)
Requires-Dist: clickhouse-driver (>=0.2.0)
Requires-Dist: lxml (>=4.5.0)
Requires-Dist: pika (>=1.2.1)
Requires-Dist: rocketmq-client-python (>=2.0.0)
Requires-Dist: numpy (==1.23.5)
Requires-Dist: filetype (>=1.2.0)
Requires-Dist: python3-memcached (>=1.51)
Requires-Dist: urllib3 (==1.26.15)
Requires-Dist: nacos-sdk-python (==1.0.0)
Requires-Dist: pymongo (==4.10.1)
